<library path="lib/libassistant_tcp_interface_plugins">
  
  <class type="assistant_tcp_interface::AssistantClient" base_class_type="assistant_tcp_interface::AssistantClientBase">
    <description>
      This is a client tcp interface for the Assistant project.
    </description>
  </class>
  
  <class type="assistant_tcp_interface::AssistantServer" base_class_type="assistant_tcp_interface::AssistantServerBase">
    <description>
      This is a server tcp interface for the Assistant project.
    </description> 
  </class>

</library>
